{
  "timestamp": "2026-05-08T07:21:57.976Z",
  "overall": "degraded",
  "metrics": {
    "status": "degraded",
    "operationalPercentage": 50,
    "averageResponseTime": 1122,
    "sitesWithIssues": [
      {
        "id": "blog",
        "name": "DevOps Blog",
        "status": "degraded",
        "statusText": "Client Error"
      },
      {
        "id": "cloud",
        "name": "Cloud Blog",
        "status": "degraded",
        "statusText": "Client Error"
      },
      {
        "id": "docker2k8s",
        "name": "Docker to Kubernetes",
        "status": "degraded",
        "statusText": "Slow Response"
      },
      {
        "id": "devopslab",
        "name": "DevOps Engineering Lab",
        "status": "degraded",
        "statusText": "Client Error"
      },
      {
        "id": "toolguides",
        "name": "DevOps Tool Guides",
        "status": "degraded",
        "statusText": "Client Error"
      }
    ],
    "totalSites": 10
  },
  "sites": [
    {
      "id": "projects",
      "name": "Real-Time Projects Hub",
      "url": "https://projects.prodevopsguytech.com",
      "icon": "💻",
      "description": "Hands-on DevOps projects from beginner to advanced",
      "status": "operational",
      "statusText": "Operational",
      "statusCode": 200,
      "responseTime": 205,
      "error": null,
      "lastChecked": "2026-05-08T07:21:53.093Z"
    },
    {
      "id": "docs",
      "name": "Ultimate Docs Portal",
      "url": "https://docs.prodevopsguytech.com",
      "icon": "📚",
      "description": "900+ curated DevOps learning materials",
      "status": "operational",
      "statusText": "Operational",
      "statusCode": 200,
      "responseTime": 2621,
      "error": null,
      "lastChecked": "2026-05-08T07:21:55.541Z"
    },
    {
      "id": "repos",
      "name": "Repositories Central",
      "url": "https://repos.prodevopsguytech.com",
      "icon": "📦",
      "description": "Collection of scripts, infrastructure code & prep content",
      "status": "operational",
      "statusText": "Operational",
      "statusCode": 200,
      "responseTime": 287,
      "error": null,
      "lastChecked": "2026-05-08T07:21:53.209Z"
    },
    {
      "id": "jobs",
      "name": "Jobs Portal",
      "url": "https://jobs.prodevopsguytech.com",
      "icon": "🧭",
      "description": "Find your next DevOps career opportunity",
      "status": "operational",
      "statusText": "Operational",
      "statusCode": 200,
      "responseTime": 2067,
      "error": null,
      "lastChecked": "2026-05-08T07:21:54.990Z"
    },
    {
      "id": "blog",
      "name": "DevOps Blog",
      "url": "https://blog.prodevopsguytech.com",
      "icon": "📰",
      "description": "Deep dives into DevOps practices & tutorials",
      "status": "degraded",
      "statusText": "Client Error",
      "statusCode": 429,
      "responseTime": 333,
      "error": null,
      "lastChecked": "2026-05-08T07:21:53.257Z"
    },
    {
      "id": "cloud",
      "name": "Cloud Blog",
      "url": "https://cloud.prodevopsguytech.com",
      "icon": "☁️",
      "description": "Cloud architecture & implementation guides",
      "status": "degraded",
      "statusText": "Client Error",
      "statusCode": 429,
      "responseTime": 337,
      "error": null,
      "lastChecked": "2026-05-08T07:21:53.262Z"
    },
    {
      "id": "docker2k8s",
      "name": "Docker to Kubernetes",
      "url": "https://dockertokubernetes.live",
      "icon": "🐳",
      "description": "Master containerization journey",
      "status": "degraded",
      "statusText": "Slow Response",
      "statusCode": 200,
      "responseTime": 5048,
      "error": null,
      "lastChecked": "2026-05-08T07:21:57.974Z"
    },
    {
      "id": "devopslab",
      "name": "DevOps Engineering Lab",
      "url": "https://www.devops-engineering.site",
      "icon": "🔬",
      "description": "Hands-on CI/CD & automation",
      "status": "degraded",
      "statusText": "Client Error",
      "statusCode": 404,
      "responseTime": 385,
      "error": null,
      "lastChecked": "2026-05-08T07:21:53.312Z"
    },
    {
      "id": "toolguides",
      "name": "DevOps Tool Guides",
      "url": "https://www.devopsguides.site",
      "icon": "🛠️",
      "description": "Setup & installation guides",
      "status": "degraded",
      "statusText": "Client Error",
      "statusCode": 404,
      "responseTime": 535,
      "error": null,
      "lastChecked": "2026-05-08T07:21:53.463Z"
    },
    {
      "id": "cheatsheet",
      "name": "DevOps Cheatsheet",
      "url": "https://cheatsheet.prodevopsguytech.com",
      "icon": "📑",
      "description": "Comprehensive tools & practices",
      "status": "operational",
      "statusText": "Operational",
      "statusCode": 200,
      "responseTime": 429,
      "error": null,
      "lastChecked": "2026-05-08T07:21:53.358Z"
    }
  ],
  "lastChecked": "2026-05-08T07:21:57.976Z",
  "historical": {
    "hourly": {
      "projects": {
        "2026-05-07T08": {
          "status": "operational",
          "responseTime": 317
        },
        "2026-05-07T13": {
          "status": "operational",
          "responseTime": 303
        },
        "2026-05-07T19": {
          "status": "operational",
          "responseTime": 232
        },
        "2026-05-08T02": {
          "status": "operational",
          "responseTime": 537
        },
        "2026-05-08T07": {
          "status": "operational",
          "responseTime": 205
        }
      },
      "docs": {
        "2026-05-07T08": {
          "status": "operational",
          "responseTime": 2500
        },
        "2026-05-07T13": {
          "status": "operational",
          "responseTime": 1266
        },
        "2026-05-07T19": {
          "status": "operational",
          "responseTime": 2218
        },
        "2026-05-08T02": {
          "status": "operational",
          "responseTime": 1094
        },
        "2026-05-08T07": {
          "status": "operational",
          "responseTime": 2621
        }
      },
      "repos": {
        "2026-05-07T08": {
          "status": "operational",
          "responseTime": 342
        },
        "2026-05-07T13": {
          "status": "operational",
          "responseTime": 381
        },
        "2026-05-07T19": {
          "status": "operational",
          "responseTime": 245
        },
        "2026-05-08T02": {
          "status": "operational",
          "responseTime": 560
        },
        "2026-05-08T07": {
          "status": "operational",
          "responseTime": 287
        }
      },
      "jobs": {
        "2026-05-07T08": {
          "status": "operational",
          "responseTime": 1619
        },
        "2026-05-07T13": {
          "status": "operational",
          "responseTime": 2679
        },
        "2026-05-07T19": {
          "status": "operational",
          "responseTime": 2178
        },
        "2026-05-08T02": {
          "status": "operational",
          "responseTime": 2214
        },
        "2026-05-08T07": {
          "status": "operational",
          "responseTime": 2067
        }
      },
      "blog": {
        "2026-05-07T08": {
          "status": "degraded",
          "responseTime": 343
        },
        "2026-05-07T13": {
          "status": "degraded",
          "responseTime": 396
        },
        "2026-05-07T19": {
          "status": "degraded",
          "responseTime": 351
        },
        "2026-05-08T02": {
          "status": "degraded",
          "responseTime": 326
        },
        "2026-05-08T07": {
          "status": "degraded",
          "responseTime": 333
        }
      },
      "cloud": {
        "2026-05-07T08": {
          "status": "degraded",
          "responseTime": 377
        },
        "2026-05-07T13": {
          "status": "degraded",
          "responseTime": 359
        },
        "2026-05-07T19": {
          "status": "degraded",
          "responseTime": 421
        },
        "2026-05-08T02": {
          "status": "degraded",
          "responseTime": 544
        },
        "2026-05-08T07": {
          "status": "degraded",
          "responseTime": 337
        }
      },
      "docker2k8s": {
        "2026-05-07T08": {
          "status": "degraded",
          "responseTime": 4806
        },
        "2026-05-07T13": {
          "status": "degraded",
          "responseTime": 5282
        },
        "2026-05-07T19": {
          "status": "operational",
          "responseTime": 1748
        },
        "2026-05-08T02": {
          "status": "degraded",
          "responseTime": 5557
        },
        "2026-05-08T07": {
          "status": "degraded",
          "responseTime": 5048
        }
      },
      "devopslab": {
        "2026-05-07T08": {
          "status": "degraded",
          "responseTime": 516
        },
        "2026-05-07T13": {
          "status": "degraded",
          "responseTime": 479
        },
        "2026-05-07T19": {
          "status": "degraded",
          "responseTime": 538
        },
        "2026-05-08T02": {
          "status": "degraded",
          "responseTime": 613
        },
        "2026-05-08T07": {
          "status": "degraded",
          "responseTime": 385
        }
      },
      "toolguides": {
        "2026-05-07T08": {
          "status": "degraded",
          "responseTime": 539
        },
        "2026-05-07T13": {
          "status": "degraded",
          "responseTime": 554
        },
        "2026-05-07T19": {
          "status": "degraded",
          "responseTime": 648
        },
        "2026-05-08T02": {
          "status": "degraded",
          "responseTime": 595
        },
        "2026-05-08T07": {
          "status": "degraded",
          "responseTime": 535
        }
      },
      "cheatsheet": {
        "2026-05-07T08": {
          "status": "operational",
          "responseTime": 973
        },
        "2026-05-07T13": {
          "status": "operational",
          "responseTime": 571
        },
        "2026-05-07T19": {
          "status": "operational",
          "responseTime": 682
        },
        "2026-05-08T02": {
          "status": "operational",
          "responseTime": 809
        },
        "2026-05-08T07": {
          "status": "operational",
          "responseTime": 429
        }
      }
    },
    "daily": {
      "projects": {
        "2026-05-01": {
          "checks": 4,
          "operational": 4,
          "degraded": 0,
          "outage": 0,
          "totalResponseTime": 932,
          "uptime": 100,
          "avgResponseTime": 233
        },
        "2026-05-02": {
          "checks": 4,
          "operational": 4,
          "degraded": 0,
          "outage": 0,
          "totalResponseTime": 671,
          "uptime": 100,
          "avgResponseTime": 168
        },
        "2026-05-03": {
          "checks": 4,
          "operational": 4,
          "degraded": 0,
          "outage": 0,
          "totalResponseTime": 905,
          "uptime": 100,
          "avgResponseTime": 226
        },
        "2026-05-04": {
          "checks": 4,
          "operational": 4,
          "degraded": 0,
          "outage": 0,
          "totalResponseTime": 654,
          "uptime": 100,
          "avgResponseTime": 164
        },
        "2026-05-05": {
          "checks": 3,
          "operational": 3,
          "degraded": 0,
          "outage": 0,
          "totalResponseTime": 556,
          "uptime": 100,
          "avgResponseTime": 185
        },
        "2026-05-06": {
          "checks": 3,
          "operational": 3,
          "degraded": 0,
          "outage": 0,
          "totalResponseTime": 754,
          "uptime": 100,
          "avgResponseTime": 251
        },
        "2026-05-07": {
          "checks": 4,
          "operational": 4,
          "degraded": 0,
          "outage": 0,
          "totalResponseTime": 960,
          "uptime": 100,
          "avgResponseTime": 240
        },
        "2026-05-08": {
          "checks": 2,
          "operational": 2,
          "degraded": 0,
          "outage": 0,
          "totalResponseTime": 742,
          "uptime": 100,
          "avgResponseTime": 371
        }
      },
      "docs": {
        "2026-05-01": {
          "checks": 4,
          "operational": 4,
          "degraded": 0,
          "outage": 0,
          "totalResponseTime": 7994,
          "uptime": 100,
          "avgResponseTime": 1999
        },
        "2026-05-02": {
          "checks": 4,
          "operational": 4,
          "degraded": 0,
          "outage": 0,
          "totalResponseTime": 9210,
          "uptime": 100,
          "avgResponseTime": 2303
        },
        "2026-05-03": {
          "checks": 4,
          "operational": 4,
          "degraded": 0,
          "outage": 0,
          "totalResponseTime": 7478,
          "uptime": 100,
          "avgResponseTime": 1870
        },
        "2026-05-04": {
          "checks": 4,
          "operational": 4,
          "degraded": 0,
          "outage": 0,
          "totalResponseTime": 6519,
          "uptime": 100,
          "avgResponseTime": 1630
        },
        "2026-05-05": {
          "checks": 3,
          "operational": 3,
          "degraded": 0,
          "outage": 0,
          "totalResponseTime": 4860,
          "uptime": 100,
          "avgResponseTime": 1620
        },
        "2026-05-06": {
          "checks": 3,
          "operational": 3,
          "degraded": 0,
          "outage": 0,
          "totalResponseTime": 5878,
          "uptime": 100,
          "avgResponseTime": 1959
        },
        "2026-05-07": {
          "checks": 4,
          "operational": 4,
          "degraded": 0,
          "outage": 0,
          "totalResponseTime": 7956,
          "uptime": 100,
          "avgResponseTime": 1989
        },
        "2026-05-08": {
          "checks": 2,
          "operational": 2,
          "degraded": 0,
          "outage": 0,
          "totalResponseTime": 3715,
          "uptime": 100,
          "avgResponseTime": 1858
        }
      },
      "repos": {
        "2026-05-01": {
          "checks": 4,
          "operational": 4,
          "degraded": 0,
          "outage": 0,
          "totalResponseTime": 1857,
          "uptime": 100,
          "avgResponseTime": 464
        },
        "2026-05-02": {
          "checks": 4,
          "operational": 4,
          "degraded": 0,
          "outage": 0,
          "totalResponseTime": 1293,
          "uptime": 100,
          "avgResponseTime": 323
        },
        "2026-05-03": {
          "checks": 4,
          "operational": 4,
          "degraded": 0,
          "outage": 0,
          "totalResponseTime": 2055,
          "uptime": 100,
          "avgResponseTime": 514
        },
        "2026-05-04": {
          "checks": 4,
          "operational": 4,
          "degraded": 0,
          "outage": 0,
          "totalResponseTime": 1574,
          "uptime": 100,
          "avgResponseTime": 394
        },
        "2026-05-05": {
          "checks": 3,
          "operational": 3,
          "degraded": 0,
          "outage": 0,
          "totalResponseTime": 1520,
          "uptime": 100,
          "avgResponseTime": 507
        },
        "2026-05-06": {
          "checks": 3,
          "operational": 3,
          "degraded": 0,
          "outage": 0,
          "totalResponseTime": 1198,
          "uptime": 100,
          "avgResponseTime": 399
        },
        "2026-05-07": {
          "checks": 4,
          "operational": 4,
          "degraded": 0,
          "outage": 0,
          "totalResponseTime": 1188,
          "uptime": 100,
          "avgResponseTime": 297
        },
        "2026-05-08": {
          "checks": 2,
          "operational": 2,
          "degraded": 0,
          "outage": 0,
          "totalResponseTime": 847,
          "uptime": 100,
          "avgResponseTime": 424
        }
      },
      "jobs": {
        "2026-05-01": {
          "checks": 4,
          "operational": 4,
          "degraded": 0,
          "outage": 0,
          "totalResponseTime": 7433,
          "uptime": 100,
          "avgResponseTime": 1858
        },
        "2026-05-02": {
          "checks": 4,
          "operational": 4,
          "degraded": 0,
          "outage": 0,
          "totalResponseTime": 7850,
          "uptime": 100,
          "avgResponseTime": 1963
        },
        "2026-05-03": {
          "checks": 4,
          "operational": 3,
          "degraded": 1,
          "outage": 0,
          "totalResponseTime": 10067,
          "uptime": 75,
          "avgResponseTime": 2517
        },
        "2026-05-04": {
          "checks": 4,
          "operational": 4,
          "degraded": 0,
          "outage": 0,
          "totalResponseTime": 7531,
          "uptime": 100,
          "avgResponseTime": 1883
        },
        "2026-05-05": {
          "checks": 3,
          "operational": 3,
          "degraded": 0,
          "outage": 0,
          "totalResponseTime": 5177,
          "uptime": 100,
          "avgResponseTime": 1726
        },
        "2026-05-06": {
          "checks": 3,
          "operational": 3,
          "degraded": 0,
          "outage": 0,
          "totalResponseTime": 5521,
          "uptime": 100,
          "avgResponseTime": 1840
        },
        "2026-05-07": {
          "checks": 4,
          "operational": 4,
          "degraded": 0,
          "outage": 0,
          "totalResponseTime": 8649,
          "uptime": 100,
          "avgResponseTime": 2162
        },
        "2026-05-08": {
          "checks": 2,
          "operational": 2,
          "degraded": 0,
          "outage": 0,
          "totalResponseTime": 4281,
          "uptime": 100,
          "avgResponseTime": 2141
        }
      },
      "blog": {
        "2026-05-01": {
          "checks": 4,
          "operational": 0,
          "degraded": 4,
          "outage": 0,
          "totalResponseTime": 1021,
          "uptime": 0,
          "avgResponseTime": 255
        },
        "2026-05-02": {
          "checks": 4,
          "operational": 0,
          "degraded": 4,
          "outage": 0,
          "totalResponseTime": 1904,
          "uptime": 0,
          "avgResponseTime": 476
        },
        "2026-05-03": {
          "checks": 4,
          "operational": 0,
          "degraded": 4,
          "outage": 0,
          "totalResponseTime": 1469,
          "uptime": 0,
          "avgResponseTime": 367
        },
        "2026-05-04": {
          "checks": 4,
          "operational": 0,
          "degraded": 4,
          "outage": 0,
          "totalResponseTime": 1089,
          "uptime": 0,
          "avgResponseTime": 272
        },
        "2026-05-05": {
          "checks": 3,
          "operational": 0,
          "degraded": 3,
          "outage": 0,
          "totalResponseTime": 401,
          "uptime": 0,
          "avgResponseTime": 134
        },
        "2026-05-06": {
          "checks": 3,
          "operational": 0,
          "degraded": 3,
          "outage": 0,
          "totalResponseTime": 1045,
          "uptime": 0,
          "avgResponseTime": 348
        },
        "2026-05-07": {
          "checks": 4,
          "operational": 0,
          "degraded": 4,
          "outage": 0,
          "totalResponseTime": 1193,
          "uptime": 0,
          "avgResponseTime": 298
        },
        "2026-05-08": {
          "checks": 2,
          "operational": 0,
          "degraded": 2,
          "outage": 0,
          "totalResponseTime": 659,
          "uptime": 0,
          "avgResponseTime": 330
        }
      },
      "cloud": {
        "2026-05-01": {
          "checks": 4,
          "operational": 0,
          "degraded": 4,
          "outage": 0,
          "totalResponseTime": 1233,
          "uptime": 0,
          "avgResponseTime": 308
        },
        "2026-05-02": {
          "checks": 4,
          "operational": 0,
          "degraded": 4,
          "outage": 0,
          "totalResponseTime": 1893,
          "uptime": 0,
          "avgResponseTime": 473
        },
        "2026-05-03": {
          "checks": 4,
          "operational": 0,
          "degraded": 4,
          "outage": 0,
          "totalResponseTime": 1896,
          "uptime": 0,
          "avgResponseTime": 474
        },
        "2026-05-04": {
          "checks": 4,
          "operational": 0,
          "degraded": 4,
          "outage": 0,
          "totalResponseTime": 1273,
          "uptime": 0,
          "avgResponseTime": 318
        },
        "2026-05-05": {
          "checks": 3,
          "operational": 0,
          "degraded": 3,
          "outage": 0,
          "totalResponseTime": 528,
          "uptime": 0,
          "avgResponseTime": 176
        },
        "2026-05-06": {
          "checks": 3,
          "operational": 0,
          "degraded": 3,
          "outage": 0,
          "totalResponseTime": 1091,
          "uptime": 0,
          "avgResponseTime": 364
        },
        "2026-05-07": {
          "checks": 4,
          "operational": 0,
          "degraded": 4,
          "outage": 0,
          "totalResponseTime": 1265,
          "uptime": 0,
          "avgResponseTime": 316
        },
        "2026-05-08": {
          "checks": 2,
          "operational": 0,
          "degraded": 2,
          "outage": 0,
          "totalResponseTime": 881,
          "uptime": 0,
          "avgResponseTime": 441
        }
      },
      "docker2k8s": {
        "2026-05-01": {
          "checks": 4,
          "operational": 0,
          "degraded": 4,
          "outage": 0,
          "totalResponseTime": 20693,
          "uptime": 0,
          "avgResponseTime": 5173
        },
        "2026-05-02": {
          "checks": 4,
          "operational": 1,
          "degraded": 3,
          "outage": 0,
          "totalResponseTime": 17253,
          "uptime": 25,
          "avgResponseTime": 4313
        },
        "2026-05-03": {
          "checks": 4,
          "operational": 2,
          "degraded": 2,
          "outage": 0,
          "totalResponseTime": 13061,
          "uptime": 50,
          "avgResponseTime": 3265
        },
        "2026-05-04": {
          "checks": 4,
          "operational": 1,
          "degraded": 3,
          "outage": 0,
          "totalResponseTime": 16318,
          "uptime": 25,
          "avgResponseTime": 4080
        },
        "2026-05-05": {
          "checks": 3,
          "operational": 2,
          "degraded": 1,
          "outage": 0,
          "totalResponseTime": 9243,
          "uptime": 67,
          "avgResponseTime": 3081
        },
        "2026-05-06": {
          "checks": 3,
          "operational": 2,
          "degraded": 1,
          "outage": 0,
          "totalResponseTime": 8722,
          "uptime": 67,
          "avgResponseTime": 2907
        },
        "2026-05-07": {
          "checks": 4,
          "operational": 2,
          "degraded": 2,
          "outage": 0,
          "totalResponseTime": 13591,
          "uptime": 50,
          "avgResponseTime": 3398
        },
        "2026-05-08": {
          "checks": 2,
          "operational": 0,
          "degraded": 2,
          "outage": 0,
          "totalResponseTime": 10605,
          "uptime": 0,
          "avgResponseTime": 5303
        }
      },
      "devopslab": {
        "2026-05-01": {
          "checks": 4,
          "operational": 0,
          "degraded": 4,
          "outage": 0,
          "totalResponseTime": 1673,
          "uptime": 0,
          "avgResponseTime": 418
        },
        "2026-05-02": {
          "checks": 4,
          "operational": 0,
          "degraded": 4,
          "outage": 0,
          "totalResponseTime": 2329,
          "uptime": 0,
          "avgResponseTime": 582
        },
        "2026-05-03": {
          "checks": 4,
          "operational": 0,
          "degraded": 4,
          "outage": 0,
          "totalResponseTime": 2041,
          "uptime": 0,
          "avgResponseTime": 510
        },
        "2026-05-04": {
          "checks": 4,
          "operational": 0,
          "degraded": 4,
          "outage": 0,
          "totalResponseTime": 1678,
          "uptime": 0,
          "avgResponseTime": 420
        },
        "2026-05-05": {
          "checks": 3,
          "operational": 0,
          "degraded": 3,
          "outage": 0,
          "totalResponseTime": 577,
          "uptime": 0,
          "avgResponseTime": 192
        },
        "2026-05-06": {
          "checks": 3,
          "operational": 0,
          "degraded": 3,
          "outage": 0,
          "totalResponseTime": 1321,
          "uptime": 0,
          "avgResponseTime": 440
        },
        "2026-05-07": {
          "checks": 4,
          "operational": 0,
          "degraded": 4,
          "outage": 0,
          "totalResponseTime": 1674,
          "uptime": 0,
          "avgResponseTime": 419
        },
        "2026-05-08": {
          "checks": 2,
          "operational": 0,
          "degraded": 2,
          "outage": 0,
          "totalResponseTime": 998,
          "uptime": 0,
          "avgResponseTime": 499
        }
      },
      "toolguides": {
        "2026-05-01": {
          "checks": 4,
          "operational": 0,
          "degraded": 4,
          "outage": 0,
          "totalResponseTime": 1944,
          "uptime": 0,
          "avgResponseTime": 486
        },
        "2026-05-02": {
          "checks": 4,
          "operational": 0,
          "degraded": 4,
          "outage": 0,
          "totalResponseTime": 2557,
          "uptime": 0,
          "avgResponseTime": 639
        },
        "2026-05-03": {
          "checks": 4,
          "operational": 0,
          "degraded": 4,
          "outage": 0,
          "totalResponseTime": 2575,
          "uptime": 0,
          "avgResponseTime": 644
        },
        "2026-05-04": {
          "checks": 4,
          "operational": 0,
          "degraded": 4,
          "outage": 0,
          "totalResponseTime": 2123,
          "uptime": 0,
          "avgResponseTime": 531
        },
        "2026-05-05": {
          "checks": 3,
          "operational": 0,
          "degraded": 3,
          "outage": 0,
          "totalResponseTime": 847,
          "uptime": 0,
          "avgResponseTime": 282
        },
        "2026-05-06": {
          "checks": 3,
          "operational": 0,
          "degraded": 3,
          "outage": 0,
          "totalResponseTime": 1617,
          "uptime": 0,
          "avgResponseTime": 539
        },
        "2026-05-07": {
          "checks": 4,
          "operational": 0,
          "degraded": 4,
          "outage": 0,
          "totalResponseTime": 1956,
          "uptime": 0,
          "avgResponseTime": 489
        },
        "2026-05-08": {
          "checks": 2,
          "operational": 0,
          "degraded": 2,
          "outage": 0,
          "totalResponseTime": 1130,
          "uptime": 0,
          "avgResponseTime": 565
        }
      },
      "cheatsheet": {
        "2026-05-01": {
          "checks": 4,
          "operational": 4,
          "degraded": 0,
          "outage": 0,
          "totalResponseTime": 2622,
          "uptime": 100,
          "avgResponseTime": 656
        },
        "2026-05-02": {
          "checks": 4,
          "operational": 4,
          "degraded": 0,
          "outage": 0,
          "totalResponseTime": 2978,
          "uptime": 100,
          "avgResponseTime": 745
        },
        "2026-05-03": {
          "checks": 4,
          "operational": 4,
          "degraded": 0,
          "outage": 0,
          "totalResponseTime": 3056,
          "uptime": 100,
          "avgResponseTime": 764
        },
        "2026-05-04": {
          "checks": 4,
          "operational": 4,
          "degraded": 0,
          "outage": 0,
          "totalResponseTime": 2264,
          "uptime": 100,
          "avgResponseTime": 566
        },
        "2026-05-05": {
          "checks": 3,
          "operational": 3,
          "degraded": 0,
          "outage": 0,
          "totalResponseTime": 1012,
          "uptime": 100,
          "avgResponseTime": 337
        },
        "2026-05-06": {
          "checks": 3,
          "operational": 3,
          "degraded": 0,
          "outage": 0,
          "totalResponseTime": 1980,
          "uptime": 100,
          "avgResponseTime": 660
        },
        "2026-05-07": {
          "checks": 4,
          "operational": 4,
          "degraded": 0,
          "outage": 0,
          "totalResponseTime": 2402,
          "uptime": 100,
          "avgResponseTime": 601
        },
        "2026-05-08": {
          "checks": 2,
          "operational": 2,
          "degraded": 0,
          "outage": 0,
          "totalResponseTime": 1238,
          "uptime": 100,
          "avgResponseTime": 619
        }
      }
    }
  }
}