{
  "timestamp": "2025-12-23T18:23:44.313Z",
  "overall": "degraded",
  "metrics": {
    "status": "degraded",
    "operationalPercentage": 80,
    "averageResponseTime": 813,
    "sitesWithIssues": [
      {
        "id": "blog",
        "name": "DevOps Blog",
        "status": "degraded",
        "statusText": "Client Error"
      },
      {
        "id": "cloud",
        "name": "Cloud Blog",
        "status": "degraded",
        "statusText": "Client Error"
      }
    ],
    "totalSites": 10
  },
  "sites": [
    {
      "id": "projects",
      "name": "Real-Time Projects Hub",
      "url": "https://projects.prodevopsguytech.com",
      "icon": "💻",
      "description": "Hands-on DevOps projects from beginner to advanced",
      "status": "operational",
      "statusText": "Operational",
      "statusCode": 200,
      "responseTime": 184,
      "error": null,
      "lastChecked": "2025-12-23T18:23:42.003Z"
    },
    {
      "id": "docs",
      "name": "Ultimate Docs Portal",
      "url": "https://docs.prodevopsguytech.com",
      "icon": "📚",
      "description": "900+ curated DevOps learning materials",
      "status": "operational",
      "statusText": "Operational",
      "statusCode": 200,
      "responseTime": 2463,
      "error": null,
      "lastChecked": "2025-12-23T18:23:44.312Z"
    },
    {
      "id": "repos",
      "name": "Repositories Central",
      "url": "https://repos.prodevopsguytech.com",
      "icon": "📦",
      "description": "Collection of scripts, infrastructure code & prep content",
      "status": "operational",
      "statusText": "Operational",
      "statusCode": 200,
      "responseTime": 239,
      "error": null,
      "lastChecked": "2025-12-23T18:23:42.089Z"
    },
    {
      "id": "jobs",
      "name": "Jobs Portal",
      "url": "https://jobs.prodevopsguytech.com",
      "icon": "🧭",
      "description": "Find your next DevOps career opportunity",
      "status": "operational",
      "statusText": "Operational",
      "statusCode": 200,
      "responseTime": 1265,
      "error": null,
      "lastChecked": "2025-12-23T18:23:43.117Z"
    },
    {
      "id": "blog",
      "name": "DevOps Blog",
      "url": "https://blog.prodevopsguytech.com",
      "icon": "📰",
      "description": "Deep dives into DevOps practices & tutorials",
      "status": "degraded",
      "statusText": "Client Error",
      "statusCode": 429,
      "responseTime": 214,
      "error": null,
      "lastChecked": "2025-12-23T18:23:42.066Z"
    },
    {
      "id": "cloud",
      "name": "Cloud Blog",
      "url": "https://cloud.prodevopsguytech.com",
      "icon": "☁️",
      "description": "Cloud architecture & implementation guides",
      "status": "degraded",
      "statusText": "Client Error",
      "statusCode": 429,
      "responseTime": 312,
      "error": null,
      "lastChecked": "2025-12-23T18:23:42.165Z"
    },
    {
      "id": "docker2k8s",
      "name": "Docker to Kubernetes",
      "url": "https://dockertokubernetes.live",
      "icon": "🐳",
      "description": "Master containerization journey",
      "status": "operational",
      "statusText": "Operational",
      "statusCode": 200,
      "responseTime": 1255,
      "error": null,
      "lastChecked": "2025-12-23T18:23:43.109Z"
    },
    {
      "id": "devopslab",
      "name": "DevOps Engineering Lab",
      "url": "https://www.devops-engineering.site",
      "icon": "🔬",
      "description": "Hands-on CI/CD & automation",
      "status": "operational",
      "statusText": "Operational",
      "statusCode": 200,
      "responseTime": 271,
      "error": null,
      "lastChecked": "2025-12-23T18:23:42.126Z"
    },
    {
      "id": "toolguides",
      "name": "DevOps Tool Guides",
      "url": "https://www.devopsguides.site",
      "icon": "🛠️",
      "description": "Setup & installation guides",
      "status": "operational",
      "statusText": "Operational",
      "statusCode": 200,
      "responseTime": 359,
      "error": null,
      "lastChecked": "2025-12-23T18:23:42.215Z"
    },
    {
      "id": "cheatsheet",
      "name": "DevOps Cheatsheet",
      "url": "https://cheatsheet.prodevopsguytech.com",
      "icon": "📑",
      "description": "Comprehensive tools & practices",
      "status": "operational",
      "statusText": "Operational",
      "statusCode": 200,
      "responseTime": 470,
      "error": null,
      "lastChecked": "2025-12-23T18:23:42.327Z"
    }
  ],
  "lastChecked": "2025-12-23T18:23:44.313Z",
  "historical": {
    "hourly": {
      "projects": {
        "2025-12-22T18": {
          "status": "operational",
          "responseTime": 691
        },
        "2025-12-23T01": {
          "status": "operational",
          "responseTime": 125
        },
        "2025-12-23T06": {
          "status": "operational",
          "responseTime": 502
        },
        "2025-12-23T12": {
          "status": "operational",
          "responseTime": 276
        },
        "2025-12-23T18": {
          "status": "operational",
          "responseTime": 184
        }
      },
      "docs": {
        "2025-12-22T18": {
          "status": "operational",
          "responseTime": 2823
        },
        "2025-12-23T01": {
          "status": "operational",
          "responseTime": 2320
        },
        "2025-12-23T06": {
          "status": "operational",
          "responseTime": 2541
        },
        "2025-12-23T12": {
          "status": "operational",
          "responseTime": 2537
        },
        "2025-12-23T18": {
          "status": "operational",
          "responseTime": 2463
        }
      },
      "repos": {
        "2025-12-22T18": {
          "status": "operational",
          "responseTime": 370
        },
        "2025-12-23T01": {
          "status": "operational",
          "responseTime": 658
        },
        "2025-12-23T06": {
          "status": "operational",
          "responseTime": 407
        },
        "2025-12-23T12": {
          "status": "operational",
          "responseTime": 434
        },
        "2025-12-23T18": {
          "status": "operational",
          "responseTime": 239
        }
      },
      "jobs": {
        "2025-12-22T18": {
          "status": "operational",
          "responseTime": 967
        },
        "2025-12-23T01": {
          "status": "operational",
          "responseTime": 1245
        },
        "2025-12-23T06": {
          "status": "operational",
          "responseTime": 366
        },
        "2025-12-23T12": {
          "status": "operational",
          "responseTime": 1259
        },
        "2025-12-23T18": {
          "status": "operational",
          "responseTime": 1265
        }
      },
      "blog": {
        "2025-12-22T18": {
          "status": "degraded",
          "responseTime": 519
        },
        "2025-12-23T01": {
          "status": "degraded",
          "responseTime": 416
        },
        "2025-12-23T06": {
          "status": "degraded",
          "responseTime": 411
        },
        "2025-12-23T12": {
          "status": "degraded",
          "responseTime": 318
        },
        "2025-12-23T18": {
          "status": "degraded",
          "responseTime": 214
        }
      },
      "cloud": {
        "2025-12-22T18": {
          "status": "degraded",
          "responseTime": 569
        },
        "2025-12-23T01": {
          "status": "degraded",
          "responseTime": 408
        },
        "2025-12-23T06": {
          "status": "degraded",
          "responseTime": 489
        },
        "2025-12-23T12": {
          "status": "degraded",
          "responseTime": 470
        },
        "2025-12-23T18": {
          "status": "degraded",
          "responseTime": 312
        }
      },
      "docker2k8s": {
        "2025-12-22T18": {
          "status": "degraded",
          "responseTime": 5905
        },
        "2025-12-23T01": {
          "status": "degraded",
          "responseTime": 5463
        },
        "2025-12-23T06": {
          "status": "degraded",
          "responseTime": 5446
        },
        "2025-12-23T12": {
          "status": "degraded",
          "responseTime": 5124
        },
        "2025-12-23T18": {
          "status": "operational",
          "responseTime": 1255
        }
      },
      "devopslab": {
        "2025-12-22T18": {
          "status": "operational",
          "responseTime": 664
        },
        "2025-12-23T01": {
          "status": "operational",
          "responseTime": 683
        },
        "2025-12-23T06": {
          "status": "operational",
          "responseTime": 669
        },
        "2025-12-23T12": {
          "status": "operational",
          "responseTime": 522
        },
        "2025-12-23T18": {
          "status": "operational",
          "responseTime": 271
        }
      },
      "toolguides": {
        "2025-12-22T18": {
          "status": "operational",
          "responseTime": 893
        },
        "2025-12-23T01": {
          "status": "operational",
          "responseTime": 673
        },
        "2025-12-23T06": {
          "status": "operational",
          "responseTime": 1077
        },
        "2025-12-23T12": {
          "status": "operational",
          "responseTime": 821
        },
        "2025-12-23T18": {
          "status": "operational",
          "responseTime": 359
        }
      },
      "cheatsheet": {
        "2025-12-22T18": {
          "status": "operational",
          "responseTime": 966
        },
        "2025-12-23T01": {
          "status": "operational",
          "responseTime": 677
        },
        "2025-12-23T06": {
          "status": "operational",
          "responseTime": 896
        },
        "2025-12-23T12": {
          "status": "operational",
          "responseTime": 678
        },
        "2025-12-23T18": {
          "status": "operational",
          "responseTime": 470
        }
      }
    },
    "daily": {
      "projects": {
        "2025-12-16": {
          "checks": 4,
          "operational": 4,
          "degraded": 0,
          "outage": 0,
          "totalResponseTime": 752,
          "uptime": 100,
          "avgResponseTime": 188
        },
        "2025-12-17": {
          "checks": 4,
          "operational": 4,
          "degraded": 0,
          "outage": 0,
          "totalResponseTime": 1420,
          "uptime": 100,
          "avgResponseTime": 355
        },
        "2025-12-18": {
          "checks": 4,
          "operational": 4,
          "degraded": 0,
          "outage": 0,
          "totalResponseTime": 1305,
          "uptime": 100,
          "avgResponseTime": 326
        },
        "2025-12-19": {
          "checks": 4,
          "operational": 4,
          "degraded": 0,
          "outage": 0,
          "totalResponseTime": 572,
          "uptime": 100,
          "avgResponseTime": 143
        },
        "2025-12-20": {
          "checks": 4,
          "operational": 4,
          "degraded": 0,
          "outage": 0,
          "totalResponseTime": 1206,
          "uptime": 100,
          "avgResponseTime": 302
        },
        "2025-12-21": {
          "checks": 4,
          "operational": 4,
          "degraded": 0,
          "outage": 0,
          "totalResponseTime": 641,
          "uptime": 100,
          "avgResponseTime": 160
        },
        "2025-12-22": {
          "checks": 4,
          "operational": 4,
          "degraded": 0,
          "outage": 0,
          "totalResponseTime": 1455,
          "uptime": 100,
          "avgResponseTime": 364
        },
        "2025-12-23": {
          "checks": 4,
          "operational": 4,
          "degraded": 0,
          "outage": 0,
          "totalResponseTime": 1087,
          "uptime": 100,
          "avgResponseTime": 272
        }
      },
      "docs": {
        "2025-12-16": {
          "checks": 4,
          "operational": 4,
          "degraded": 0,
          "outage": 0,
          "totalResponseTime": 7688,
          "uptime": 100,
          "avgResponseTime": 1922
        },
        "2025-12-17": {
          "checks": 4,
          "operational": 3,
          "degraded": 1,
          "outage": 0,
          "totalResponseTime": 13916,
          "uptime": 75,
          "avgResponseTime": 3479
        },
        "2025-12-18": {
          "checks": 4,
          "operational": 4,
          "degraded": 0,
          "outage": 0,
          "totalResponseTime": 9863,
          "uptime": 100,
          "avgResponseTime": 2466
        },
        "2025-12-19": {
          "checks": 4,
          "operational": 4,
          "degraded": 0,
          "outage": 0,
          "totalResponseTime": 9297,
          "uptime": 100,
          "avgResponseTime": 2324
        },
        "2025-12-20": {
          "checks": 4,
          "operational": 3,
          "degraded": 1,
          "outage": 0,
          "totalResponseTime": 7689,
          "uptime": 75,
          "avgResponseTime": 1922
        },
        "2025-12-21": {
          "checks": 4,
          "operational": 4,
          "degraded": 0,
          "outage": 0,
          "totalResponseTime": 9280,
          "uptime": 100,
          "avgResponseTime": 2320
        },
        "2025-12-22": {
          "checks": 4,
          "operational": 4,
          "degraded": 0,
          "outage": 0,
          "totalResponseTime": 9451,
          "uptime": 100,
          "avgResponseTime": 2363
        },
        "2025-12-23": {
          "checks": 4,
          "operational": 4,
          "degraded": 0,
          "outage": 0,
          "totalResponseTime": 9861,
          "uptime": 100,
          "avgResponseTime": 2465
        }
      },
      "repos": {
        "2025-12-16": {
          "checks": 4,
          "operational": 4,
          "degraded": 0,
          "outage": 0,
          "totalResponseTime": 1397,
          "uptime": 100,
          "avgResponseTime": 349
        },
        "2025-12-17": {
          "checks": 4,
          "operational": 4,
          "degraded": 0,
          "outage": 0,
          "totalResponseTime": 2396,
          "uptime": 100,
          "avgResponseTime": 599
        },
        "2025-12-18": {
          "checks": 4,
          "operational": 4,
          "degraded": 0,
          "outage": 0,
          "totalResponseTime": 1326,
          "uptime": 100,
          "avgResponseTime": 332
        },
        "2025-12-19": {
          "checks": 4,
          "operational": 4,
          "degraded": 0,
          "outage": 0,
          "totalResponseTime": 927,
          "uptime": 100,
          "avgResponseTime": 232
        },
        "2025-12-20": {
          "checks": 4,
          "operational": 4,
          "degraded": 0,
          "outage": 0,
          "totalResponseTime": 2092,
          "uptime": 100,
          "avgResponseTime": 523
        },
        "2025-12-21": {
          "checks": 4,
          "operational": 4,
          "degraded": 0,
          "outage": 0,
          "totalResponseTime": 1002,
          "uptime": 100,
          "avgResponseTime": 251
        },
        "2025-12-22": {
          "checks": 4,
          "operational": 4,
          "degraded": 0,
          "outage": 0,
          "totalResponseTime": 1856,
          "uptime": 100,
          "avgResponseTime": 464
        },
        "2025-12-23": {
          "checks": 4,
          "operational": 4,
          "degraded": 0,
          "outage": 0,
          "totalResponseTime": 1738,
          "uptime": 100,
          "avgResponseTime": 435
        }
      },
      "jobs": {
        "2025-12-16": {
          "checks": 4,
          "operational": 4,
          "degraded": 0,
          "outage": 0,
          "totalResponseTime": 4101,
          "uptime": 100,
          "avgResponseTime": 1025
        },
        "2025-12-17": {
          "checks": 4,
          "operational": 4,
          "degraded": 0,
          "outage": 0,
          "totalResponseTime": 6460,
          "uptime": 100,
          "avgResponseTime": 1615
        },
        "2025-12-18": {
          "checks": 4,
          "operational": 4,
          "degraded": 0,
          "outage": 0,
          "totalResponseTime": 5172,
          "uptime": 100,
          "avgResponseTime": 1293
        },
        "2025-12-19": {
          "checks": 4,
          "operational": 4,
          "degraded": 0,
          "outage": 0,
          "totalResponseTime": 4946,
          "uptime": 100,
          "avgResponseTime": 1237
        },
        "2025-12-20": {
          "checks": 4,
          "operational": 4,
          "degraded": 0,
          "outage": 0,
          "totalResponseTime": 4420,
          "uptime": 100,
          "avgResponseTime": 1105
        },
        "2025-12-21": {
          "checks": 4,
          "operational": 4,
          "degraded": 0,
          "outage": 0,
          "totalResponseTime": 3634,
          "uptime": 100,
          "avgResponseTime": 909
        },
        "2025-12-22": {
          "checks": 4,
          "operational": 4,
          "degraded": 0,
          "outage": 0,
          "totalResponseTime": 4579,
          "uptime": 100,
          "avgResponseTime": 1145
        },
        "2025-12-23": {
          "checks": 4,
          "operational": 4,
          "degraded": 0,
          "outage": 0,
          "totalResponseTime": 4135,
          "uptime": 100,
          "avgResponseTime": 1034
        }
      },
      "blog": {
        "2025-12-16": {
          "checks": 4,
          "operational": 0,
          "degraded": 4,
          "outage": 0,
          "totalResponseTime": 1460,
          "uptime": 0,
          "avgResponseTime": 365
        },
        "2025-12-17": {
          "checks": 4,
          "operational": 0,
          "degraded": 4,
          "outage": 0,
          "totalResponseTime": 1841,
          "uptime": 0,
          "avgResponseTime": 460
        },
        "2025-12-18": {
          "checks": 4,
          "operational": 0,
          "degraded": 4,
          "outage": 0,
          "totalResponseTime": 1525,
          "uptime": 0,
          "avgResponseTime": 381
        },
        "2025-12-19": {
          "checks": 4,
          "operational": 0,
          "degraded": 4,
          "outage": 0,
          "totalResponseTime": 1144,
          "uptime": 0,
          "avgResponseTime": 286
        },
        "2025-12-20": {
          "checks": 4,
          "operational": 0,
          "degraded": 4,
          "outage": 0,
          "totalResponseTime": 1629,
          "uptime": 0,
          "avgResponseTime": 407
        },
        "2025-12-21": {
          "checks": 4,
          "operational": 0,
          "degraded": 4,
          "outage": 0,
          "totalResponseTime": 1196,
          "uptime": 0,
          "avgResponseTime": 299
        },
        "2025-12-22": {
          "checks": 4,
          "operational": 0,
          "degraded": 4,
          "outage": 0,
          "totalResponseTime": 1551,
          "uptime": 0,
          "avgResponseTime": 388
        },
        "2025-12-23": {
          "checks": 4,
          "operational": 0,
          "degraded": 4,
          "outage": 0,
          "totalResponseTime": 1359,
          "uptime": 0,
          "avgResponseTime": 340
        }
      },
      "cloud": {
        "2025-12-16": {
          "checks": 4,
          "operational": 0,
          "degraded": 4,
          "outage": 0,
          "totalResponseTime": 1484,
          "uptime": 0,
          "avgResponseTime": 371
        },
        "2025-12-17": {
          "checks": 4,
          "operational": 0,
          "degraded": 4,
          "outage": 0,
          "totalResponseTime": 2122,
          "uptime": 0,
          "avgResponseTime": 531
        },
        "2025-12-18": {
          "checks": 4,
          "operational": 0,
          "degraded": 4,
          "outage": 0,
          "totalResponseTime": 1516,
          "uptime": 0,
          "avgResponseTime": 379
        },
        "2025-12-19": {
          "checks": 4,
          "operational": 0,
          "degraded": 4,
          "outage": 0,
          "totalResponseTime": 1807,
          "uptime": 0,
          "avgResponseTime": 452
        },
        "2025-12-20": {
          "checks": 4,
          "operational": 0,
          "degraded": 4,
          "outage": 0,
          "totalResponseTime": 1764,
          "uptime": 0,
          "avgResponseTime": 441
        },
        "2025-12-21": {
          "checks": 4,
          "operational": 0,
          "degraded": 4,
          "outage": 0,
          "totalResponseTime": 1240,
          "uptime": 0,
          "avgResponseTime": 310
        },
        "2025-12-22": {
          "checks": 4,
          "operational": 0,
          "degraded": 4,
          "outage": 0,
          "totalResponseTime": 1744,
          "uptime": 0,
          "avgResponseTime": 436
        },
        "2025-12-23": {
          "checks": 4,
          "operational": 0,
          "degraded": 4,
          "outage": 0,
          "totalResponseTime": 1679,
          "uptime": 0,
          "avgResponseTime": 420
        }
      },
      "docker2k8s": {
        "2025-12-16": {
          "checks": 4,
          "operational": 3,
          "degraded": 1,
          "outage": 0,
          "totalResponseTime": 10770,
          "uptime": 75,
          "avgResponseTime": 2693
        },
        "2025-12-17": {
          "checks": 4,
          "operational": 3,
          "degraded": 1,
          "outage": 0,
          "totalResponseTime": 12297,
          "uptime": 75,
          "avgResponseTime": 3074
        },
        "2025-12-18": {
          "checks": 4,
          "operational": 1,
          "degraded": 3,
          "outage": 0,
          "totalResponseTime": 18604,
          "uptime": 25,
          "avgResponseTime": 4651
        },
        "2025-12-19": {
          "checks": 4,
          "operational": 3,
          "degraded": 1,
          "outage": 0,
          "totalResponseTime": 11171,
          "uptime": 75,
          "avgResponseTime": 2793
        },
        "2025-12-20": {
          "checks": 4,
          "operational": 3,
          "degraded": 1,
          "outage": 0,
          "totalResponseTime": 11446,
          "uptime": 75,
          "avgResponseTime": 2862
        },
        "2025-12-21": {
          "checks": 4,
          "operational": 3,
          "degraded": 1,
          "outage": 0,
          "totalResponseTime": 15252,
          "uptime": 75,
          "avgResponseTime": 3813
        },
        "2025-12-22": {
          "checks": 4,
          "operational": 2,
          "degraded": 2,
          "outage": 0,
          "totalResponseTime": 14964,
          "uptime": 50,
          "avgResponseTime": 3741
        },
        "2025-12-23": {
          "checks": 4,
          "operational": 1,
          "degraded": 3,
          "outage": 0,
          "totalResponseTime": 17288,
          "uptime": 25,
          "avgResponseTime": 4322
        }
      },
      "devopslab": {
        "2025-12-16": {
          "checks": 4,
          "operational": 4,
          "degraded": 0,
          "outage": 0,
          "totalResponseTime": 2297,
          "uptime": 100,
          "avgResponseTime": 574
        },
        "2025-12-17": {
          "checks": 4,
          "operational": 4,
          "degraded": 0,
          "outage": 0,
          "totalResponseTime": 2852,
          "uptime": 100,
          "avgResponseTime": 713
        },
        "2025-12-18": {
          "checks": 4,
          "operational": 4,
          "degraded": 0,
          "outage": 0,
          "totalResponseTime": 2336,
          "uptime": 100,
          "avgResponseTime": 584
        },
        "2025-12-19": {
          "checks": 4,
          "operational": 4,
          "degraded": 0,
          "outage": 0,
          "totalResponseTime": 1754,
          "uptime": 100,
          "avgResponseTime": 439
        },
        "2025-12-20": {
          "checks": 4,
          "operational": 4,
          "degraded": 0,
          "outage": 0,
          "totalResponseTime": 2413,
          "uptime": 100,
          "avgResponseTime": 603
        },
        "2025-12-21": {
          "checks": 4,
          "operational": 4,
          "degraded": 0,
          "outage": 0,
          "totalResponseTime": 2169,
          "uptime": 100,
          "avgResponseTime": 542
        },
        "2025-12-22": {
          "checks": 4,
          "operational": 4,
          "degraded": 0,
          "outage": 0,
          "totalResponseTime": 2182,
          "uptime": 100,
          "avgResponseTime": 546
        },
        "2025-12-23": {
          "checks": 4,
          "operational": 4,
          "degraded": 0,
          "outage": 0,
          "totalResponseTime": 2145,
          "uptime": 100,
          "avgResponseTime": 536
        }
      },
      "toolguides": {
        "2025-12-16": {
          "checks": 4,
          "operational": 4,
          "degraded": 0,
          "outage": 0,
          "totalResponseTime": 2483,
          "uptime": 100,
          "avgResponseTime": 621
        },
        "2025-12-17": {
          "checks": 4,
          "operational": 4,
          "degraded": 0,
          "outage": 0,
          "totalResponseTime": 3326,
          "uptime": 100,
          "avgResponseTime": 832
        },
        "2025-12-18": {
          "checks": 4,
          "operational": 4,
          "degraded": 0,
          "outage": 0,
          "totalResponseTime": 3526,
          "uptime": 100,
          "avgResponseTime": 882
        },
        "2025-12-19": {
          "checks": 4,
          "operational": 4,
          "degraded": 0,
          "outage": 0,
          "totalResponseTime": 2086,
          "uptime": 100,
          "avgResponseTime": 522
        },
        "2025-12-20": {
          "checks": 4,
          "operational": 4,
          "degraded": 0,
          "outage": 0,
          "totalResponseTime": 3368,
          "uptime": 100,
          "avgResponseTime": 842
        },
        "2025-12-21": {
          "checks": 4,
          "operational": 4,
          "degraded": 0,
          "outage": 0,
          "totalResponseTime": 2541,
          "uptime": 100,
          "avgResponseTime": 635
        },
        "2025-12-22": {
          "checks": 4,
          "operational": 4,
          "degraded": 0,
          "outage": 0,
          "totalResponseTime": 3312,
          "uptime": 100,
          "avgResponseTime": 828
        },
        "2025-12-23": {
          "checks": 4,
          "operational": 4,
          "degraded": 0,
          "outage": 0,
          "totalResponseTime": 2930,
          "uptime": 100,
          "avgResponseTime": 733
        }
      },
      "cheatsheet": {
        "2025-12-16": {
          "checks": 4,
          "operational": 4,
          "degraded": 0,
          "outage": 0,
          "totalResponseTime": 3123,
          "uptime": 100,
          "avgResponseTime": 781
        },
        "2025-12-17": {
          "checks": 4,
          "operational": 4,
          "degraded": 0,
          "outage": 0,
          "totalResponseTime": 3419,
          "uptime": 100,
          "avgResponseTime": 855
        },
        "2025-12-18": {
          "checks": 4,
          "operational": 4,
          "degraded": 0,
          "outage": 0,
          "totalResponseTime": 2806,
          "uptime": 100,
          "avgResponseTime": 702
        },
        "2025-12-19": {
          "checks": 4,
          "operational": 4,
          "degraded": 0,
          "outage": 0,
          "totalResponseTime": 2329,
          "uptime": 100,
          "avgResponseTime": 582
        },
        "2025-12-20": {
          "checks": 4,
          "operational": 4,
          "degraded": 0,
          "outage": 0,
          "totalResponseTime": 3935,
          "uptime": 100,
          "avgResponseTime": 984
        },
        "2025-12-21": {
          "checks": 4,
          "operational": 4,
          "degraded": 0,
          "outage": 0,
          "totalResponseTime": 2734,
          "uptime": 100,
          "avgResponseTime": 684
        },
        "2025-12-22": {
          "checks": 4,
          "operational": 4,
          "degraded": 0,
          "outage": 0,
          "totalResponseTime": 3824,
          "uptime": 100,
          "avgResponseTime": 956
        },
        "2025-12-23": {
          "checks": 4,
          "operational": 4,
          "degraded": 0,
          "outage": 0,
          "totalResponseTime": 2721,
          "uptime": 100,
          "avgResponseTime": 680
        }
      }
    }
  }
}